Metadata-Version: 1.1
Name: simpbot
Version: 1.0
Summary: Simple Bot (SimpBot) - IRC (Internet Relay Chat) Bot
Home-page: http://github.com/IsmaelRLG/simpbot
Author: Ismael Lugo (kwargs)
Author-email: ismaelrlgv@gmail.com
License: UNKNOWN
Keywords: irc,bot,chat,ircbot,simplebot,simpbot
Platform: UNKNOWN
Classifier: Development Status :: 3 - Alpha
Classifier: Environment :: Console
Classifier: Intended Audience :: Developers
Classifier: License :: OSI Approved :: MIT License
Classifier: Natural Language :: Spanish
Classifier: Operating System :: POSIX :: Linux
Classifier: Operating System :: Microsoft :: Windows
Classifier: Programming Language :: Python :: 2.7
Classifier: Topic :: Communications :: Chat
